Workbook

Sheet Q1
A1: Category | B1: January | C1: February | D1: March | E1: Quarter Total
A2: Revenue
A3: Product Sales | B3: 48000 | C3: 51000 | D3: 54000 | E3: =SUM(B3:D3) -> 153000
A4: Services | B4: 18000 | C4: 19000 | D4: 20000 | E4: =SUM(B4:D4) -> 57000
A5: Licensing | B5: 9000 | C5: 9500 | D5: 10000 | E5: =SUM(B5:D5) -> 28500
A6: Total Revenue | B6: =SUM(B3:B5) -> 75000 | C6: =SUM(C3:C5) -> 79500 | D6: =SUM(D3:D5) -> 84000 | E6: =SUM(E3:E5) -> 238500
A8: Expenses
A9: Payroll | B9: 35000 | C9: 35000 | D9: 36000 | E9: =SUM(B9:D9) -> 106000
A10: Marketing | B10: 7000 | C10: 7500 | D10: 8000 | E10: =SUM(B10:D10) -> 22500
A11: Infrastructure | B11: 4500 | C11: 4500 | D11: 5000 | E11: =SUM(B11:D11) -> 14000
A12: R&D | B12: 9000 | C12: 9000 | D12: 9500 | E12: =SUM(B12:D12) -> 27500
A13: G&A | B13: 3500 | C13: 3500 | D13: 4000 | E13: =SUM(B13:D13) -> 11000
A14: Total Expenses | B14: =SUM(B9:B13) -> 59000 | C14: =SUM(C9:C13) -> 59500 | D14: =SUM(D9:D13) -> 62500 | E14: =SUM(E9:E13) -> 181000
A16: Net Income | B16: =B6-B14 -> 16000 | C16: =C6-C14 -> 20000 | D16: =D6-D14 -> 21500 | E16: =E6-E14 -> 57500

Sheet Q2
A1: Category | B1: April | C1: May | D1: June | E1: Quarter Total
A2: Revenue
A3: Product Sales | B3: 56000 | C3: 58000 | D3: 62000 | E3: =SUM(B3:D3) -> 176000
A4: Services | B4: 21000 | C4: 22000 | D4: 23000 | E4: =SUM(B4:D4) -> 66000
A5: Licensing | B5: 10500 | C5: 11000 | D5: 11500 | E5: =SUM(B5:D5) -> 33000
A6: Total Revenue | B6: =SUM(B3:B5) -> 87500 | C6: =SUM(C3:C5) -> 91000 | D6: =SUM(D3:D5) -> 96500 | E6: =SUM(E3:E5) -> 275000
A8: Expenses
A9: Payroll | B9: 36000 | C9: 36000 | D9: 37000 | E9: =SUM(B9:D9) -> 109000
A10: Marketing | B10: 8500 | C10: 9000 | D10: 9500 | E10: =SUM(B10:D10) -> 27000
A11: Infrastructure | B11: 5000 | C11: 5000 | D11: 5500 | E11: =SUM(B11:D11) -> 15500
A12: R&D | B12: 9500 | C12: 10000 | D12: 10000 | E12: =SUM(B12:D12) -> 29500
A13: G&A | B13: 4000 | C13: 4000 | D13: 4500 | E13: =SUM(B13:D13) -> 12500
A14: Total Expenses | B14: =SUM(B9:B13) -> 63000 | C14: =SUM(C9:C13) -> 64000 | D14: =SUM(D9:D13) -> 66500 | E14: =SUM(E9:E13) -> 193500
A16: Net Income | B16: =B6-B14 -> 24500 | C16: =C6-C14 -> 27000 | D16: =D6-D14 -> 30000 | E16: =E6-E14 -> 81500

Sheet Q3
A1: Category | B1: July | C1: August | D1: September | E1: Quarter Total
A2: Revenue
A3: Product Sales | B3: 60000 | C3: 59000 | D3: 63000 | E3: =SUM(B3:D3) -> 182000
A4: Services | B4: 22000 | C4: 21000 | D4: 23000 | E4: =SUM(B4:D4) -> 66000
A5: Licensing | B5: 11000 | C5: 11000 | D5: 12000 | E5: =SUM(B5:D5) -> 34000
A6: Total Revenue | B6: =SUM(B3:B5) -> 93000 | C6: =SUM(C3:C5) -> 91000 | D6: =SUM(D3:D5) -> 98000 | E6: =SUM(E3:E5) -> 282000
A8: Expenses
A9: Payroll | B9: 37000 | C9: 37000 | D9: 38000 | E9: =SUM(B9:D9) -> 112000
A10: Marketing | B10: 9000 | C10: 8500 | D10: 10000 | E10: =SUM(B10:D10) -> 27500
A11: Infrastructure | B11: 5500 | C11: 5500 | D11: 6000 | E11: =SUM(B11:D11) -> 17000
A12: R&D | B12: 10000 | C12: 10000 | D12: 11000 | E12: =SUM(B12:D12) -> 31000
A13: G&A | B13: 4000 | C13: 4000 | D13: 4500 | E13: =SUM(B13:D13) -> 12500
A14: Total Expenses | B14: =SUM(B9:B13) -> 65500 | C14: =SUM(C9:C13) -> 65000 | D14: =SUM(D9:D13) -> 69500 | E14: =SUM(E9:E13) -> 200000
A16: Net Income | B16: =B6-B14 -> 27500 | C16: =C6-C14 -> 26000 | D16: =D6-D14 -> 28500 | E16: =E6-E14 -> 82000

Sheet Q4
A1: Category | B1: October | C1: November | D1: December | E1: Quarter Total
A2: Revenue
A3: Product Sales | B3: 65000 | C3: 70000 | D3: 80000 | E3: =SUM(B3:D3) -> 215000
A4: Services | B4: 24000 | C4: 25000 | D4: 28000 | E4: =SUM(B4:D4) -> 77000
A5: Licensing | B5: 12000 | C5: 12500 | D5: 14000 | E5: =SUM(B5:D5) -> 38500
A6: Total Revenue | B6: =SUM(B3:B5) -> 101000 | C6: =SUM(C3:C5) -> 107500 | D6: =SUM(D3:D5) -> 122000 | E6: =SUM(E3:E5) -> 330500
A8: Expenses
A9: Payroll | B9: 38000 | C9: 38000 | D9: 40000 | E9: =SUM(B9:D9) -> 116000
A10: Marketing | B10: 10000 | C10: 12000 | D10: 15000 | E10: =SUM(B10:D10) -> 37000
A11: Infrastructure | B11: 6000 | C11: 6000 | D11: 7000 | E11: =SUM(B11:D11) -> 19000
A12: R&D | B12: 11000 | C12: 11000 | D12: 12000 | E12: =SUM(B12:D12) -> 34000
A13: G&A | B13: 4500 | C13: 4500 | D13: 5000 | E13: =SUM(B13:D13) -> 14000
A14: Total Expenses | B14: =SUM(B9:B13) -> 69500 | C14: =SUM(C9:C13) -> 71500 | D14: =SUM(D9:D13) -> 79000 | E14: =SUM(E9:E13) -> 220000
A16: Net Income | B16: =B6-B14 -> 31500 | C16: =C6-C14 -> 36000 | D16: =D6-D14 -> 43000 | E16: =E6-E14 -> 110500

Sheet Full Year
A1: Category | B1: Q1 | C1: Q2 | D1: Q3 | E1: Q4 | F1: Full Year
A2: Revenue | B2: ='Q1'!E6 -> 238500 | C2: ='Q2'!E6 -> 275000 | D2: ='Q3'!E6 -> 282000 | E2: ='Q4'!E6 -> 330500 | F2: =SUM(B2:E2) -> 1126000
A3: Expenses | B3: ='Q1'!E14 -> 181000 | C3: ='Q2'!E14 -> 193500 | D3: ='Q3'!E14 -> 200000 | E3: ='Q4'!E14 -> 220000 | F3: =SUM(B3:E3) -> 794500
A5: Net Income | B5: ='Q1'!E16 -> 57500 | C5: ='Q2'!E16 -> 81500 | D5: ='Q3'!E16 -> 82000 | E5: ='Q4'!E16 -> 110500 | F5: =SUM(B5:E5) -> 331500
A7: Revenue by Category | B7: Q1 | C7: Q2 | D7: Q3 | E7: Q4 | F7: Annual
A8: Product Sales | B8: 153000 | C8: 176000 | D8: 182000 | E8: 215000 | F8: =SUM(B8:E8) -> 726000
A9: Services | B9: 57000 | C9: 66000 | D9: 66000 | E9: 77000 | F9: =SUM(B9:E9) -> 266000
A10: Licensing | B10: 28500 | C10: 33000 | D10: 34000 | E10: 38500 | F10: =SUM(B10:E10) -> 134000
A12: Expenses by Category | B12: Q1 | C12: Q2 | D12: Q3 | E12: Q4 | F12: Annual
A13: Payroll | B13: 106000 | C13: 109000 | D13: 112000 | E13: 116000 | F13: =SUM(B13:E13) -> 443000
A14: Marketing | B14: 22500 | C14: 27000 | D14: 27500 | E14: 37000 | F14: =SUM(B14:E14) -> 114000
A15: Infrastructure | B15: 14000 | C15: 15500 | D15: 17000 | E15: 19000 | F15: =SUM(B15:E15) -> 65500
A16: R&D | B16: 27500 | C16: 29500 | D16: 31000 | E16: 34000 | F16: =SUM(B16:E16) -> 122000
A17: G&A | B17: 11000 | C17: 12500 | D17: 12500 | E17: 14000 | F17: =SUM(B17:E17) -> 50000
